{
  "project_info": {
    "project_number": "557294206783",
    "project_id": "skyline-boutique",
    "storage_bucket": "skyline-boutique.appspot.com"
  },
  "client": [
    {
      "client_info": {
        "mobilesdk_app_id": "1:557294206783:android:5ab88a4338fe499ac39d8a",
        "android_client_info": {
          "package_name": "seniordeveloper.peter.skylineboutique"
        }
      },
      "oauth_client": [],
      "api_key": [
        {
          "current_key": "AIzaSyCd8AO9fS0kgrdQBap9hk52KjJ8JtFxvtQ"
        }
      ],
      "services": {
        "appinvite_service": {
          "other_platform_oauth_client": []
        }
      }
    }
  ],
  "configuration_version": "1"
}